cacheia/__init__.py
cacheia/cache.py
cacheia/decorator.py
cacheia/backends/__init__.py
cacheia/backends/memory.py
cacheia/backends/mongo.py
cacheia/backends/redis.py
cacheia/backends/s3.py
cacheia/backends/utils.py
cacheia-1.0.0.post3.dist-info/METADATA
cacheia-1.0.0.post3.dist-info/WHEEL
cacheia-1.0.0.post3.dist-info/top_level.txt
cacheia-1.0.0.post3.dist-info/RECORD
