Metadata-Version: 2.1
Name: cacheia
Version: 1.0.0.post3
Summary: Cache library that allows invalidation and other shenanigans
Author-email: TeiaLabs <contato@teialabs.com>
Keywords: cache,core,lib
Requires-Python: >=3.12
Requires-Dist: pymongo <5,>=4
Requires-Dist: boto3 ~=1.34
Requires-Dist: redis <6,>=5
Requires-Dist: pydantic <3,>=2
Requires-Dist: pydantic-settings <3,>=2
Provides-Extra: dev
Requires-Dist: black <25,>=24 ; extra == 'dev'
Requires-Dist: isort <6,>=5 ; extra == 'dev'
Requires-Dist: pytest <9,>=8 ; extra == 'dev'
Provides-Extra: schemas
Requires-Dist: cacheia-schemas ==1.0.0 ; extra == 'schemas'
